{
 "absolute_value": 0,
 "align_labels_right": 0,
 "creation": "2023-11-30 09:55:09.269683",
 "css": "",
 "custom_format": 1,
 "default_print_language": "en",
 "disabled": 0,
 "doc_type": "Leave Salary Encashment",
 "docstatus": 0,
 "doctype": "Print Format",
 "font_size": 14,
 "html": "<div class=\"container\">\n    <table border=\"1\" ; width=650>\n        <tr>\n        <td colspan=\"24\"><br><img src=\"/files/Screenshot from 2022-05-16 12-39-47.png\"><br><p style=\"font-size:10px;\"></td></tr>            \n         <tr> <td  colspan=\"24\">\n         <p style='text-align:center;font-size:20px'><b>LEAVE SALARY ENCASHMENT</b></p></td>\n         </tr>\n         <tr>\n        <td colspan=\"6\" width=25%><b>Employee ID</b></td>\n        <td colspan=\"6\" width=25%>{{doc.employee or ''}}</td>\n        <td colspan=\"6\" width=25%><b>Date</b></td>\n        <td colspan=\"6\" width=25%>{{frappe.utils.format_date(doc.posting_date) or ''}}</td>\n   </tr>\n   <tr>\n        <td colspan=\"6\" width=25%><b>Employee  Name</b></td>\n        <td colspan=\"6\" width=25%>{{doc.employee_name or ''}} </td>\n        <td colspan=\"6\" width=25%><b>Date of Joining</b></td>\n        <td colspan=\"6\" width=25%>{{frappe.utils.format_date(doc.date_of_joining) or ''}}</td>\n        \n        \n   </tr>\n   <tr>\n        <td colspan=\"6\" width=25%><b>Department</b></td>\n        <td colspan=\"6\" width=25%>{{doc.department or ''}} </td>\n        <td colspan=\"6\" width=25%><b>Designation</b></td>\n        <td colspan=\"6\" width=25%>{{doc.designation or ''}}</td>\n        \n        \n   </tr>\n   <tr>\n        <td colspan=\"6\" width=25%><b>Grade</b></td>\n        <td colspan=\"6\" width=25%>{{doc.grade or ''}} </td>\n        <td colspan=\"6\" width=25%><b>Company</b></td>\n        <td colspan=\"6\" width=25%>{{doc.company or ''}}</td>\n        \n        \n   </tr>\n   <tr>\n        <td colspan=\"6\" width=25%><b>Resident ID Number</b></td>\n        <td colspan=\"6\" width=25%>{{doc.resident_id_number or ''}} </td>\n        <td colspan=\"6\" width=25%><b>Resident ID Expiry Date</b></td>\n        <td colspan=\"6\" width=25%>{{doc.resident_id_expiry_date or ''}}</td>\n        \n        \n   </tr>\n   <tr>\n        <td colspan=\"6\" width=25%><b>Passport Number</b></td>\n        <td colspan=\"6\" width=25%>{{doc.passport_number or ''}} </td>\n        <td colspan=\"6\" width=25%><b>Passport Validation</b></td>\n        <td colspan=\"6\" width=25%>{{doc.passport_validation or ''}}</td>\n        \n        \n   </tr>\n   <tr>\n        <td colspan =\"24\" style=text-align:center><b>SALARY DETAILS</b></td>\n           \n    </tr>\n    <tr>\n        <td colspan=\"6\" width=25%><b>Basic</b></td>\n        <td colspan=\"6\" width=25%>{{doc.basic or ''}} </td>\n        <td colspan=\"6\" width=25%><b>Encashment Days</b></td>\n        <td colspan=\"6\" width=25%>{{doc.encashment_days or ''}}</td>\n        \n        \n        \n   </tr>\n   <tr>\n        <td colspan=\"6\" width=25%><b>HRA</b></td>\n        <td colspan=\"6\" width=25%>{{doc.hra or ''}} </td>\n        <td colspan=\"6\" width=25%><b>Total</b></td>\n        <td colspan=\"6\" width=25%>{{doc.total or ''}}</td>\n        \n        \n        \n   </tr>\n   <tr>\n        <td colspan=\"6\" width=25%><b>Allowance</b></td>\n        <td colspan=\"6\" width=25%>{{doc.allowance or ''}} </td>\n        <td colspan=\"6\" width=25%><b>Air Ticket Allowance</b></td>\n        <td colspan=\"6\" width=25%>{{doc.air_ticket_allowance or ''}} </td>\n   </tr>\n   <tr> <td colspan=\"6\" width=25%><b>Fixed Total</b></td>\n        <td colspan=\"6\" width=25%>{{doc.fixed_total or ''}}</td>\n        <td colspan=\"6\" width=25%><b>Total LSE</b></td>\n        <td colspan=\"6\" width=25%>{{doc.total_pay or ''}}</td>\n        \n    </tr>\n    </table>\n    <p><b>Total LSE(In Words) : {{frappe.utils.money_in_words(doc.total_pay) or 0}}</b></p><br>\n    <p><b>I have received the amount QAR {{ doc.total_pay|default(0) | round(2) }}as my Total Leave Salary Encashment from the company and there is no other claim against company  so far.</b></p>\n    \n    <table>\n        <tr><td></td></tr>\n         <tr><td></td></tr>\n        <tr>\n            <td style = 'line-height: 1.9;'>\n                    Signature&nbsp;&nbsp;&nbsp;&nbsp;&nbsp;_______________________________________<br>\n                    Name&nbsp;&nbsp;&nbsp;&nbsp;&nbsp;&nbsp;&nbsp;&nbsp;&nbsp;&nbsp;&nbsp;&nbsp;_______________________________________<br>\n                    Contact No.&nbsp;&nbsp;_______________________________________<br>\n                    Date&nbsp;&nbsp;&nbsp;&nbsp;&nbsp;&nbsp;&nbsp;&nbsp;&nbsp;&nbsp;&nbsp;&nbsp;&nbsp;&nbsp;&nbsp;_______________________________________<br>\n            </td>\n        </tr>\n    </table><br><br><br>\n    <table>\n        <tr>\n        \n            <td nowrap width=50%><b>Prepared by</b></td>\n            <td nowrap width=50% ><b>Verified by</b></td>\n            <td nowrap width=50% > <b>Approved by </b></td>\n \n            \n        </tr>\n   \n    </table>\n</div>",
 "idx": 0,
 "line_breaks": 0,
 "margin_bottom": 15.0,
 "margin_left": 15.0,
 "margin_right": 15.0,
 "margin_top": 15.0,
 "modified": "2023-12-01 09:15:49.080234",
 "modified_by": "Administrator",
 "module": "Electra",
 "name": "Leave Salary Encashment",
 "owner": "Administrator",
 "page_number": "Hide",
 "print_format_builder": 0,
 "print_format_builder_beta": 0,
 "print_format_type": "Jinja",
 "raw_printing": 0,
 "show_section_headings": 0,
 "standard": "Yes"
}