{
 "absolute_value": 0,
 "align_labels_right": 0,
 "creation": "2024-02-19 10:04:12.406851",
 "css": "letter-head{\n    max-width:100px !important;\n    margin-top: -200px !important;\n}\n.foot{\n    text-align:center;\n}\n.print-format{\n    font-size:12px;\n    font-family: 'Soleto';\n    margin-left:5px;\n    margin-right:5px;\n}\nimg{\n    margin-top:-65px;\n}\n@media print\n {\n   thead {display: table-header-group;}\n }\n /*header{*/\n /*    margin-bottom:60px;*/\n /*}*/\n * {\n  box-sizing: border-box;\n  \n}\n\n.row {\n  margin-left:-5px;\n  margin-right:-5px;\n}\n  \n.column {\n  float: left;\n  width: 50%;\n  padding: 5px;\n}\n\n/* Clearfix (clear floats) */\n.row::after {\n  content: \"\";\n  clear: both;\n  display: table;\n}\ntable{\n    padding:-1px;\n}\n\n\nth, td {\n  text-align: left;\n  padding: 16px;\n}\n @page {\n       @bottom-left {\n            content: counter(page) \"https://stackoverflow.com/\" counter(pages);\n        }\n     }",
 "custom_format": 1,
 "default_print_language": "en",
 "disabled": 0,
 "doc_type": "Accounts Report Dashboard",
 "docstatus": 0,
 "doctype": "Print Format",
 "font_size": 14,
 "html": "\n\n<meta name=\"pdfkit-orientation\" content=\"Landscape\" />\n\n     {% set letter_head = frappe.db.get_value(\"Letter Head\",doc.letter_head,['image']) %}\n    <img src=\"{{ letter_head or ''  }}\" />\t\n    \n\n<p style = text-align:center>Accounts Receivable Aging Report</p>\n<p style = text-align:center><b>Posting Date :</b>{{frappe.utils.format_date(doc.from_date) or ''}} <b>To</b> {{frappe.utils.format_date(doc.to_date) or ''}}</p>\n<p style = text-align:center><b>Party :</b> {{doc.customer}}</p>\n{% set term =  frappe.db.get_value(\"Customer\", {\"name\": doc.customer},\"payment_terms\") %}\n{% if term %}\n<p style = text-align:center><b>Payment & Terms:</b> {{term}}</p>\n{% endif %}\n{% set data = ageing_report(doc)%}\n{{data}}\n\n    ",
 "idx": 0,
 "line_breaks": 0,
 "margin_bottom": 15.0,
 "margin_left": 15.0,
 "margin_right": 15.0,
 "margin_top": 15.0,
 "modified": "2024-08-28 18:40:57.699928",
 "modified_by": "Administrator",
 "module": "Electra",
 "name": "Accounts Receivable Aging Report",
 "owner": "Administrator",
 "page_number": "Hide",
 "print_format_builder": 0,
 "print_format_builder_beta": 0,
 "print_format_type": "Jinja",
 "raw_printing": 0,
 "show_section_headings": 0,
 "standard": "Yes"
}