{
 "absolute_value": 0,
 "align_labels_right": 0,
 "creation": "2024-01-01 09:28:48.345841",
 "custom_format": 1,
 "default_print_language": "en",
 "disabled": 0,
 "doc_type": "Employee Separation",
 "docstatus": 0,
 "doctype": "Print Format",
 "font_size": 14,
 "html": "\n<table border=\"1\" ; width=100%>\n    <tr>\n        <td colspan=\"4\"><img src=\"/files/Screenshot from 2022-05-16 12-39-47.png\"></td>\n        \n    </tr>\n    <tr>\n        <td colspan=\"4\"><p style='text-align:center;font-size:18px'><b>Employee Separation Form</b></p></td>\n    </tr>\n    \n</table>\n<table border=\"1\" ; width=100%>\n    <tr>\n        <td width=25%><b></b></td>\n        <td width=25%></td>\n        <td width=25%><b>Date</b></td>\n        <td width=25%>{{ frappe.utils.format_datetime(doc.creation, 'dd-MM-yyyy' or ' ')}}</td>\n    </tr>\n    <tr>\n        <td width=25%><b>Name</b></td>\n        <td width=25%>{{ doc.employee_name or ''}}</td>\n        <td width=25%><b>Employee Number</b></td>\n        <td width=25%>{{ doc .employee or ''}}</td>\n    </tr>\n    <tr>\n        <td width=25%><b>Job Title</b></td>\n        <td width=25%>{{ doc .designation or ''}}</td>\n        <td width=25%><b>Qid Number</b></td>\n        <td width=25%>{{ doc .resident_id_number or ''}}</td>\n    </tr>\n    <tr>\n        <td width=25%><b>Department</b></td>\n        <td width=25%>{{ doc .department or ''}}</td>\n        <td width=25%><b>Date of Joining</b></td>\n        <td width=25%>{{doc.get_formatted('date_of_joining1')}}</td>\n    </tr>\n</table>\n{% if doc.select == \"Resignation\" %}\n<table border=\"1\" ; width=100%>\n    <tr>\n        <td width = 25%></td>\n        {% if doc.select == \"Resignation\" %}\n        <td width = 25% style=font-size:15px;text-align:center>\u2611</td>\n        {% else %}\n        <td width = 25% style=font-size:15px></td>\n        {% endif %}\n        <td width = 50% style=font-size:10px;text-align:center><b>RESIGNATION</b></td>\n    </tr>\n</table>\n    <table border=\"1\" ; width=100% style = border-bottom-style:hidden>\n    <tr>\n        <td width=25%>Reason For Resignation</td>\n        <td width=75% style=text-align:center;>{{doc.reasons_for_resignation or ''}}</td>\n    </tr>\n</table>\n    <table border=\"1\" ; width=100%>\n    <tr>\n        <td width=\"25%\" style=\"border-top-style:hidden\"></td>\n        <td width=\"45%\" style=\"text-align:center\">Last Working Day</td>\n        <td width=\"10%\" style=\"text-align:center\">{{ frappe.utils.format_datetime(doc.last_working_day, 'dd' or ' ')}}</td>\n        <td width=\"10%\" style=\"text-align:center\">{{ frappe.utils.format_datetime(doc.last_working_day, 'MM' or ' ')}}</td>\n        <td width=\"10%\" style=\"text-align:center\">{{ frappe.utils.format_datetime(doc.last_working_day, 'yyyy' or ' ')}}</td>\n    </tr>\n\n</table>\n<table border=\"1\" ; width=100%>\n    <tr>\n        <td width=\"50%\" style = font-size:8px>I understand that, according to Article (49) of Qatar Labour Law, the worker intent to resign should provide a notification, not less than one month prior to his last working day, if the duration of service is less than 5 years/ not less than 2 months, if the duration is more than 5 years</td>\n        <td width=\"50%\" style=\"text-align:center\">Authorized By</td>\n    </tr>\n    <tr>\n        <td width=\"50%\" style = border-bottom-style:hidden><br><br></td>\n        <td width=\"50%\" style=\"text-align:center;border-bottom-style:hidden\"><br><br></td>\n    </tr>\n    <tr>\n        <td width=\"50%\" style=\"text-align:center\">Signature of Employee</td>\n        <td width=\"50%\" style=\"text-align:center\">Signature of Dept./ Div. Manager</td>\n    </tr>\n\n</table>\n{% endif %}\n{% if doc.select == \"Termination\" %}\n<table border=\"1\" ; width=100%>\n    <tr>\n        <td width = 25%></td>\n        {% if doc.select == \"Termination\" %}\n        <td width = 25% style=font-size:15px;text-align:center>\u2611</td>\n        {% else %}\n        <td width = 25% style=font-size:15px;;></td>\n        {% endif %}\n        <td width = 50% style=font-size:10px;text-align:center><b>TERMINATION</b></td>\n    </tr>\n\n</table>\n<table border=\"1\" ; width=100%>\n    <tr>\n        {% if doc.non_performance ==1 %}\n        <td width=25%>\u2611 Non Performance<br><br><br></td>\n        {% else %}\n        <td width=25%>\ud83d\udd32 Non Performance<br><br><br></td>\n        {% endif %}\n        {% if doc.medically_unfit ==1 %}\n        <td width=25%>\u2611  Medically Unfit<br><br></td>\n        {% else %}\n        <td width=25%>\ud83d\udd32 Medically Unfit<br><br></td>\n        {% endif %}\n        {% if doc.disciplinary_action ==1 %}\n        <td width=25%>\u2611  Disciplinary Action<br><br></td>\n        {% else %}\n        <td width=25%>\ud83d\udd32 Disciplinary Action<br><br></td>\n        {% endif %}\n        <td width=25%>Authorized By<br><br></td>\n    </tr>\n    </table>\n    <table border=\"1\" ; width=100%>\n    <tr>\n       {% if doc.other_document ==1 %}\n        <td width=26%><br><br>\u2611 Other Reasons </td>\n        {% else %}\n        <td width=26%><br><br>\ud83d\udd32 Other Reasons</td>\n        {% endif %} \n        <td width=\"25%\" style=\"text-align:center\"><br><br>Last Working Day</td>\n        <td width=\"5%\" style=\"text-align:center\"><br><br>{{ frappe.utils.format_datetime(doc.boarding_begins_on, 'dd' or ' ')}}</td>\n        <td width=\"5%\" style=\"text-align:center\"><br><br>{{ frappe.utils.format_datetime(doc.boarding_begins_on, 'MM' or ' ')}}</td>\n        <td width=\"5%\" style=\"text-align:center\"><br><br>{{ frappe.utils.format_datetime(doc.boarding_begins_on, 'yyyy' or ' ')}}</td>\n        <td width=\"35%\" style=\"text-align:center\"><br><br>Department Manager / Division Manager</td>\n    </tr>\n</table>\n{% endif %}\n <table border=\"1\" ; width=100%>\n     <tr>\n         <td width=100% style=text-align:center>HR Use Only</td>\n     </tr>\n</table>\n<table border=\"1\" ; width=100%>\n    <tr>\n        <td width=25%>Employee Status:</td>\n        {% if doc.employment_status ==\"Under Probation\" %}\n        <td width=35%>\u2611  Under Probation </td>\n        {% else %}\n        <td width=35%>\ud83d\udd32 Under Probation<br><br></td>\n        {% endif %}\n        {% if doc.employment_status ==\"Confirmed Employee\" %}\n        <td width=35%>\u2611  Confirmed Employee </td>\n        {% else %}\n        <td width=35%>\ud83d\udd32 Confirmed Employee<br><br></td>\n        {% endif %}\n    </tr>\n</table>\n<table border=\"1\" ; width=100%>\n    <tr>\n        <td width = 15%>Legal Entitlements</td>\n        {% if doc.due_salary ==1 %}\n        <td width=10%>\u2611   </td>\n        {% else %}\n        <td width=10%>\ud83d\udd32 </td>\n        {% endif %}\n        <td width = 10%>Due Salary</td>\n        {% if doc.leave_salary ==1 %}\n        <td width=10%>\u2611   </td>\n        {% else %}\n        <td width=10%>\ud83d\udd32 </td>\n        {% endif %}\n        <td width = 10%>Leave Salary</td>\n        {% if doc.repatriation_ ==1 %}\n        <td width=10%>\u2611   </td>\n        {% else %}\n        <td width=10%>\ud83d\udd32 </td>\n        {% endif %}\n        <td width = 10%>Repatriation</td>\n    </tr>\n    <tr>\n        <td width = 15% style = border-top-style:hidden>(Tick Appropriate Boxes, as per eligibility)</td>\n        {% if doc.notice_period_pay ==1 %}\n        <td width=10%>\u2611   </td>\n        {% else %}\n        <td width=10%>\ud83d\udd32 </td>\n        {% endif %}\n        <td width = 10%>Notice Period Pay</td>\n        {% if doc.end ==1 %}\n        <td width=10%>\u2611   </td>\n        {% else %}\n        <td width=10%>\ud83d\udd32 </td>\n        {% endif %}\n        <td width = 10%>End of Service</td>\n        {% if doc.visa_cancel_ ==1 %}\n        <td width=10%>\u2611   </td>\n        {% else %}\n        <td width=10%>\ud83d\udd32 </td>\n        {% endif %}\n        <td width = 10%>Visa Cancel</td>\n    </tr>\n</table>\n<table border=\"1\" ; width=100%>\n    <tr>\n        <td width=35% style=text-align:center>Processed by</td>\n        <td width=30% style=text-align:center>Verified by </td>\n        <td width=35% style=text-align:center>Final Approval by</td>\n    </tr>\n    <tr>\n        <td width=35% style=text-align:center><br><br></td>\n        <td width=30% style=text-align:center><br><br></td>\n        <td width=35% style=text-align:center><br><br></td>\n    </tr>\n    <tr>\n        <td width=35% style=text-align:center>HR & Admin Manager</td>\n        <td width=30% style=text-align:center>Finance Department</td>\n        <td width=35% style=text-align:center>Managing Director</td>\n    </tr>\n</table>\n<table border=\"1\" ; width=100%>\n    <tr>\n        <td width=100% style = font-size:8px>Note: Enclose separate Resignation Letter, in case of resignation and for Termination, enclose appropriate documents along with this form.</td>\n    </tr>\n    </table>",
 "idx": 0,
 "line_breaks": 0,
 "margin_bottom": 15.0,
 "margin_left": 15.0,
 "margin_right": 15.0,
 "margin_top": 15.0,
 "modified": "2025-02-05 10:39:57.550450",
 "modified_by": "divya.p@groupteampro.com",
 "module": "Electra",
 "name": "Employee Separation",
 "page_number": "Hide",
 "print_format_builder": 0,
 "print_format_builder_beta": 0,
 "print_format_type": "Jinja",
 "raw_printing": 0,
 "show_section_headings": 0,
 "standard": "Yes"
}